mccloud/__init__.py
mccloud/cli.py
mccloud/cloudy.py
mccloud/config.py
mccloud/constants.py
mccloud/utils.py
mccloud/version.py
mccloud/commands/__init__.py
mccloud/commands/ansible.py
mccloud/commands/connect.py
mccloud/commands/packer.py
mccloud/commands/setup.py
mccloud/commands/terraform.py
mccloud/commands/utils.py
mccloud-0.0.14.dist-info/LICENSE
mccloud-0.0.14.dist-info/METADATA
mccloud-0.0.14.dist-info/WHEEL
mccloud-0.0.14.dist-info/entry_points.txt
mccloud-0.0.14.dist-info/top_level.txt
mccloud-0.0.14.dist-info/RECORD
